metaa_ai_api/__init__.py
metaa_ai_api/metaa_ai_api.py
metaa_ai_api-0.0.4.dist-info/LICENSE.txt
metaa_ai_api-0.0.4.dist-info/METADATA
metaa_ai_api-0.0.4.dist-info/WHEEL
metaa_ai_api-0.0.4.dist-info/top_level.txt
metaa_ai_api-0.0.4.dist-info/RECORD
